genedom/BarcodesCollection.py
genedom/DomesticationResult.py
genedom/StandardDomesticatorsSet.py
genedom/__init__.py
genedom/batch_domestication.py
genedom/biotools.py
genedom/builtin_standards.py
genedom/reports.py
genedom/version.py
genedom/PartDomesticator/GoldenGateDomesticator.py
genedom/PartDomesticator/PartDomesticator.py
genedom/PartDomesticator/__init__.py
genedom/assembly_standards/EMMA.csv
genedom/assembly_standards/YTK.csv
genedom/reports_assets/domestication_report.pug
genedom/reports_assets/report_style.css
genedom/reports_assets/imgs/check.png
genedom/reports_assets/imgs/fail.png
genedom/reports_assets/imgs/logo.png
genedom/reports_assets/imgs/pass.png
genedom-0.2.2.dist-info/licenses/LICENSE
genedom-0.2.2.dist-info/METADATA
genedom-0.2.2.dist-info/WHEEL
genedom-0.2.2.dist-info/top_level.txt
genedom-0.2.2.dist-info/RECORD
