Metadata-Version: 2.4
Name: genedom
Version: 0.2.2
Summary: Genetic part standardization
Author: Zulko
License-Expression: MIT
Project-URL: Homepage, https://github.com/Edinburgh-Genome-Foundry/genedom
Keywords: genetic,DNA,part,standardization,synthetic biology
License-File: LICENSE
Requires-Dist: dnachisel[reports]
Requires-Dist: snapgene_reader
Requires-Dist: pdf_reports
Requires-Dist: pandas
Requires-Dist: dna_features_viewer
Requires-Dist: python-box
Requires-Dist: openpyxl
Requires-Dist: flametree
Requires-Dist: sequenticon
Dynamic: license-file
